cmdrx/__init__.py
cmdrx/cli.py
cmdrx/config.py
cmdrx/core.py
cmdrx/exceptions.py
cmdrx/llm.py
cmdrx/output.py
cmdrx-0.2.1.dist-info/licenses/LICENSE
cmdrx-0.2.1.dist-info/METADATA
cmdrx-0.2.1.dist-info/WHEEL
cmdrx-0.2.1.dist-info/entry_points.txt
cmdrx-0.2.1.dist-info/top_level.txt
cmdrx-0.2.1.dist-info/RECORD
