Metadata-Version: 2.4
Name: cmdrx
Version: 0.2.1
Summary: AI-powered command line troubleshooting tool
Author-email: CmdRx Team <team@cmdrx.dev>
License-Expression: MIT
Project-URL: Homepage, https://github.com/cmdrx/cmdrx
Project-URL: Repository, https://github.com/cmdrx/cmdrx
Project-URL: Issues, https://github.com/cmdrx/cmdrx/issues
Project-URL: Documentation, https://cmdrx.readthedocs.io
Keywords: cli,troubleshooting,ai,llm,sysadmin
Classifier: Development Status :: 3 - Alpha
Classifier: Environment :: Console
Classifier: Intended Audience :: System Administrators
Classifier: Operating System :: POSIX :: Linux
Classifier: Operating System :: MacOS
Classifier: Programming Language :: Python :: 3
Classifier: Programming Language :: Python :: 3.8
Classifier: Programming Language :: Python :: 3.9
Classifier: Programming Language :: Python :: 3.10
Classifier: Programming Language :: Python :: 3.11
Classifier: Programming Language :: Python :: 3.12
Classifier: Topic :: System :: Systems Administration
Classifier: Topic :: Utilities
License-File: LICENSE
Requires-Dist: click>=8.0.0
Requires-Dist: rich>=13.0.0
Requires-Dist: requests>=2.28.0
Requires-Dist: keyring>=24.0.0
Requires-Dist: openai>=1.0.0
Requires-Dist: cryptography>=3.4.0
Requires-Dist: pydantic>=2.0.0
Requires-Dist: textual>=0.40.0
Provides-Extra: dev
Requires-Dist: pytest>=7.0.0; extra == "dev"
Requires-Dist: pytest-cov>=4.0.0; extra == "dev"
Requires-Dist: pytest-mock>=3.10.0; extra == "dev"
Requires-Dist: black>=23.0.0; extra == "dev"
Requires-Dist: isort>=5.12.0; extra == "dev"
Requires-Dist: flake8>=6.0.0; extra == "dev"
Requires-Dist: mypy>=1.0.0; extra == "dev"
Dynamic: license-file
